vatools/__init__.py
vatools/ref_transcript_mismatch_reporter.py
vatools/transform_split_values.py
vatools/vcf_expression_annotator.py
vatools/vcf_genotype_annotator.py
vatools/vcf_info_annotator.py
vatools/vcf_readcount_annotator.py
vatools/vep_annotation_reporter.py
vatools-5.2.0.dist-info/LICENSE
vatools-5.2.0.dist-info/METADATA
vatools-5.2.0.dist-info/WHEEL
vatools-5.2.0.dist-info/entry_points.txt
vatools-5.2.0.dist-info/top_level.txt
vatools-5.2.0.dist-info/RECORD
