Metadata-Version: 2.1
Name: vatools
Version: 5.2.0
Summary: A tool for annotating VCF files with expression and readcount data
Home-page: https://github.com/griffithlab/vatools
Author: Susanna Kiwala, Chris Miller
Author-email: help@vatools.org
License: MIT License
Keywords: cancer sequencing variant variants gene expression readcounts VAF allele frequency FPKM TPM transcript VCF
Classifier: Development Status :: 5 - Production/Stable
Classifier: Intended Audience :: Science/Research
Classifier: Topic :: Scientific/Engineering :: Bio-Informatics
Classifier: Programming Language :: Python :: 3.5
Classifier: License :: OSI Approved :: MIT License
License-File: LICENSE
Requires-Dist: vcfpy (==0.12.3)
Requires-Dist: pysam
Requires-Dist: pandas
Requires-Dist: gtfparse (==1.3.0)
Requires-Dist: testfixtures
